MANIFEST.in
README.rst
README.txt
requirements.txt
setup.py
TTFramework/DevelopMain.py
TTFramework/TestMain.py
TTFramework/__init__.py
TTFramework.egg-info/PKG-INFO
TTFramework.egg-info/SOURCES.txt
TTFramework.egg-info/dependency_links.txt
TTFramework.egg-info/requires.txt
TTFramework.egg-info/top_level.txt
TTFramework/Conf/__init__.py
TTFramework/Conf/fastDfsClient.conf
TTFramework/Core/Base.py
TTFramework/Core/Configer.py
TTFramework/Core/ConnectionPostgres.py
TTFramework/Core/DatetimePlus.py
TTFramework/Core/Encryption.py
TTFramework/Core/FastDfsManager.py
TTFramework/Core/FileManager.py
TTFramework/Core/FuncHelper.py
TTFramework/Core/HttpTesterBase.py
TTFramework/Core/InstanceFactory.py
TTFramework/Core/InterfaceBase.py
TTFramework/Core/InterfaceManager.py
TTFramework/Core/LDAPManager.py
TTFramework/Core/Logger.py
TTFramework/Core/Permissions.py
TTFramework/Core/ServiceBase.py
TTFramework/Core/ServiceManager.py
TTFramework/Core/SessionManager.py
TTFramework/Core/Statistics.py
TTFramework/Core/__init__.py
TTFramework/Models/__init__.py
TTFramework/TTAdmin/TTAdmin.py
TTFramework/TTAdmin/static/ttlogo.png
TTFramework/TTAdmin/static/css/bootstrap.min.css
TTFramework/TTAdmin/static/css/font-awesome.css
TTFramework/TTAdmin/static/css/style-responsive.css
TTFramework/TTAdmin/static/css/style.css
TTFramework/TTAdmin/static/echart/.DS_Store
TTFramework/TTAdmin/static/echart/echarts.js
TTFramework/TTAdmin/static/echart/chart/bar.js
TTFramework/TTAdmin/static/echart/chart/line.js
TTFramework/TTAdmin/static/fonts/FontAwesome.otf
TTFramework/TTAdmin/static/fonts/fontawesome-webfont.eot
TTFramework/TTAdmin/static/fonts/fontawesome-webfont.svg
TTFramework/TTAdmin/static/fonts/fontawesome-webfont.ttf
TTFramework/TTAdmin/static/fonts/fontawesome-webfont.woff
TTFramework/TTAdmin/static/fonts/fontawesome-webfont.woff2
TTFramework/TTAdmin/static/fonts/glyphicons-halflings-regular.woff
TTFramework/TTAdmin/static/fonts/glyphicons-halflings-regular.woff2
TTFramework/TTAdmin/static/images/bg.jpg
TTFramework/TTAdmin/static/images/close.png
TTFramework/TTAdmin/static/images/mail.png
TTFramework/TTAdmin/static/images/minimal.png
